pypackage_auto_publish/__init__.py
pypackage_auto_publish/greetings.py
pypackage_auto_publish/py.typed
pypackage_auto_publish-0.0.4.dist-info/WHEEL
pypackage_auto_publish-0.0.4.dist-info/METADATA
pypackage_auto_publish-0.0.4.dist-info/RECORD
