Metadata-Version: 2.1
Name: pypackage-auto-publish
Version: 0.0.4
Summary: A sample package with best practices
Home-page: https://namuan.github.io/pypackage-auto-publish
License: MIT
Author: namuan
Author-email: github@deskriders.dev
Requires-Python: >=3.7.1,<4.0
Classifier: Development Status :: 4 - Beta
Classifier: Intended Audience :: Developers
Classifier: License :: OSI Approved :: MIT License
Classifier: Operating System :: OS Independent
Classifier: Programming Language :: Python
Classifier: Programming Language :: Python :: 3
Classifier: Programming Language :: Python :: 3.10
Classifier: Programming Language :: Python :: 3.7
Classifier: Programming Language :: Python :: 3.8
Classifier: Programming Language :: Python :: 3.9
Classifier: Topic :: Software Development :: Libraries :: Python Modules
Classifier: Typing :: Typed
Project-URL: Documentation, https://namuan.github.io/pypackage-auto-publish
Project-URL: Repository, https://github.com/namuan/pypackage-auto-publish
